{
  "id": "i-dle",
  "name": "I-dle",
  "category": "girlGroup",
  "parentGroupId": null,
  "generation": "4",
  "debutYear": 2018,
  "status": "active",
  "company": "Cube Entertainment",
  "coverImage": "/assets/groups/i-dle/cover.webp",
  "members": [
    {
      "idolId": "soyeon",
      "status": "current",
      "roles": [
        "vocal",
        "leader",
        "mainRapper"
      ]
    },
    {
      "idolId": "miyeon",
      "status": "current",
      "roles": [
        "mainVocal",
        "dancer",
        "visual"
      ]
    },
    {
      "idolId": "minnie",
      "status": "current",
      "roles": [
        "mainVocal",
        "dancer"
      ]
    },
    {
      "idolId": "soojin",
      "status": "former",
      "roles": [
        "vocal",
        "mainDancer",
        "rapper"
      ]
    },
    {
      "idolId": "yuqi",
      "status": "current",
      "roles": [
        "vocal",
        "visual",
        "rapper",
        "mainDancer"
      ]
    },
    {
      "idolId": "shuhua",
      "status": "current",
      "roles": [
        "vocal",
        "dancer",
        "maknae"
      ]
    }
  ],
  "discography": {
    "titles": [
      {
        "id": "latata",
        "title": "Latata",
        "youtubeUrl": "https://youtu.be/p4RIhcY7V3c?si=Sls2eFYT7uWcZ1Hw",
        "isDebutSong": true
      },
      {
        "id": "the-good-thing",
        "title": "The Good Thing",
        "youtubeUrl": "https://youtu.be/hAONx6nuEgI?si=M_PWPvtXERWXINcp"
      },
      {
        "id": "mono-en",
        "title": "MONO",
        "youtubeUrl": "https://youtu.be/DYgE3SGPEqk?si=o3HuZxi8oV84qJFe",
        "language": "en"
      },
      {
        "id": "i-want-that-en",
        "title": "I Want That",
        "youtubeUrl": "https://youtu.be/Iewisp9KYRw?si=--zAZhF6O5ZwQX9W",
        "language": "en"
      },
      {
        "id": "i-do-en",
        "title": "I Do",
        "youtubeUrl": "https://youtu.be/pCh3Kp6qxo8?si=YRMDVPRJPW46DW_D",
        "language": "en"
      },
      {
        "id": "fate-jp",
        "title": "Fate",
        "youtubeUrl": "https://youtu.be/ATK7gAaZTOM?si=FHgxM1_55shD07q2",
        "language": "jp"
      },
      {
        "id": "allergy",
        "title": "Allergy",
        "youtubeUrl": "https://youtu.be/XZaBkbvteBc?si=V1rYu0xvDuSD4pP0"
      },
      {
        "id": "hann-alone",
        "title": "HANN (Alone)",
        "youtubeUrl": "https://youtu.be/OKNXn2qCEws?si=DYe2otRUUsumuN3Z"
      },
      {
        "id": "senorita",
        "title": "Senorita",
        "youtubeUrl": "https://youtu.be/2cevbhEqQF4?si=e4837uHI1XDZxjht"
      },
      {
        "id": "uh-oh",
        "title": "Uh-Oh",
        "youtubeUrl": "https://youtu.be/I66oFXdf0KU?si=QCtv5g_BwiHLVV83"
      },
      {
        "id": "lion",
        "title": "Lion",
        "youtubeUrl": "https://youtu.be/6oanIo_2Z4Q?si=FY-FX4qWZZUoi4XH"
      },
      {
        "id": "oh-my-god",
        "title": "Oh My God",
        "youtubeUrl": "https://youtu.be/om3n2ni8luE?si=f-aoW__AtsFQdbfj"
      },
      {
        "id": "dumdi-dumdi",
        "title": "Dumdi Dumdi",
        "youtubeUrl": "https://youtu.be/HPQ5mqovXHo?si=Oic1LvjTFUIQ5Hez"
      },
      {
        "id": "hwaa",
        "title": "HWAA",
        "youtubeUrl": "https://youtu.be/z3szNvgQxHo?si=pFcDp2QUI8d0Zeze"
      },
      {
        "id": "super-lady",
        "title": "Super Lady",
        "youtubeUrl": "https://youtu.be/6f3RzjXPQwA?si=_uygwzl2_IwDPIoQ"
      },
      {
        "id": "tomboy-kr",
        "title": "Tomboy",
        "youtubeUrl": "https://youtu.be/Jh4QFaPmdss?si=n104tuCePIcwO4Uh",
        "language": "kr"
      },
      {
        "id": "nxde",
        "title": "Nxde",
        "youtubeUrl": "https://youtu.be/fCO7f0SmrDc?si=5ksv18ScUVZbp3vW"
      },
      {
        "id": "queencard-kr",
        "title": "Queencard",
        "youtubeUrl": "https://youtu.be/7HDeem-JaSY?si=GU1miHEnS8Vj_NRI",
        "language": "kr"
      }
    ],
    "bSides": [
      {
        "id": "my-bag",
        "title": "My Bag",
        "youtubeUrl": "https://youtu.be/cnBV09Ux2S0?si=31ANfiHrUoQj-6m4"
      },
      {
        "id": "maze",
        "title": "MAZE",
        "youtubeUrl": "https://youtu.be/aRfqzT84rYg?si=8ynMvkaQIwQxaX5f"
      },
      {
        "id": "already",
        "title": "Already",
        "youtubeUrl": "https://youtu.be/9Bp42n1hxOY?si=1QmK-RDvadZJwJQ8"
      },
      {
        "id": "paradise",
        "title": "Paradise",
        "youtubeUrl": "https://youtu.be/PCbx5U-S5ec?si=rl4CpknY67DWPI3Y"
      },
      {
        "id": "dahlia",
        "title": "Dahlia",
        "youtubeUrl": "https://youtu.be/adl0yFg8Ntc?si=upG-2s-ZbL1VUw4x"
      },
      {
        "id": "lost",
        "title": "Lost",
        "youtubeUrl": "https://youtu.be/ILmHLmZiVG0?si=xyzMgd22A90MW0uh"
      },
      {
        "id": "moon",
        "title": "Moon",
        "youtubeUrl": "https://youtu.be/OYtjo3CTAOM?si=lyvTw_IlOv1Ydt1j"
      },
      {
        "id": "where-is-love",
        "title": "Where Is Love",
        "youtubeUrl": "https://youtu.be/L4WnbelD60E?si=YPbBszQCqs9B8UGh"
      },
      {
        "id": "hann-alone-in-winter",
        "title": " HANN (Alone in winter)",
        "youtubeUrl": "https://youtu.be/HwC58-_VIpo?si=YftYrgUZSzBhDEqG"
      },
      {
        "id": "put-it-straight",
        "title": "Put It Straight",
        "youtubeUrl": "https://youtu.be/MIAtuJ31l98?si=qmzc8MVfcuWjJSCz"
      },
      {
        "id": "change",
        "title": "Change",
        "youtubeUrl": "https://youtu.be/bjFMG8BT144?si=hOv9_DIm8Ophajq5"
      }
    ]
  },
  "fandomName": "Neverland",
  "notes": null
}